printannotate/__init__.py
printannotate/__main__.py
printannotate/simple_annotate.py
printannotate/traced_annotate.py
tests/__init__.py
tests/test_main.py
printannotate-0.0.1.dist-info/LICENSE
printannotate-0.0.1.dist-info/METADATA
printannotate-0.0.1.dist-info/WHEEL
printannotate-0.0.1.dist-info/entry_points.txt
printannotate-0.0.1.dist-info/top_level.txt
printannotate-0.0.1.dist-info/RECORD
