Metadata-Version: 2.1
Name: printannotate
Version: 0.0.1
Summary: A package to annotate print statements in provided script.
Home-page: https://github.com/saikotek/printannotate
Author: Andrzej Wasowski
Author-email: me@wasowski.dev
Classifier: Programming Language :: Python :: 3
Classifier: License :: OSI Approved :: MIT License
Classifier: Operating System :: OS Independent
Requires-Python: >=3.6
License-File: LICENSE
